anymessage/__init__.py
anymessage/client.py
anymessage-0.1.0.dist-info/LICENSE
anymessage-0.1.0.dist-info/METADATA
anymessage-0.1.0.dist-info/WHEEL
anymessage-0.1.0.dist-info/RECORD
