Metadata-Version: 2.3
Name: anymessage
Version: 0.1.0
Summary: Asynchronous Python SDK for AnyMessage email service
License: MIT
Keywords: anymessage,sdk,async,email,api
Author: Alexander
Author-email: xuizzoee@gmail.com
Requires-Python: >=3.8
Classifier: License :: OSI Approved :: MIT License
Classifier: Operating System :: OS Independent
Classifier: Programming Language :: Python :: 3
Classifier: Programming Language :: Python :: 3.8
Classifier: Programming Language :: Python :: 3.9
Classifier: Programming Language :: Python :: 3.10
Classifier: Programming Language :: Python :: 3.11
Classifier: Programming Language :: Python :: 3.12
Classifier: Programming Language :: Python :: 3.13
Requires-Dist: aiohttp (>=3.8.0)
Project-URL: Homepage, https://github.com/whoissoee/anymessage-sdk
Project-URL: Repository, https://github.com/whoissoee/anymessage-sdk
